MANIFEST.in
main.py
setup.cfg
Eridium/MANIFEST.in
Eridium/__init__.py
Eridium/setup.cfg
Eridium/setup.py
Eridium.egg-info/PKG-INFO
Eridium.egg-info/SOURCES.txt
Eridium.egg-info/dependency_links.txt
Eridium.egg-info/top_level.txt
Eridium-1.5.dist-info/METADATA
Eridium-1.5.dist-info/WHEEL
Eridium-1.5.dist-info/top_level.txt
Eridium-1.5.dist-info/RECORD
