Metadata-Version: 2.1
Name: Eridium
Version: 1.5
Summary: Simple Math
Author: Darkester
Author-email: chernaev.alex@mail.ru
Classifier: Programming Language :: Python :: 3
Classifier: License :: OSI Approved :: MIT License
Classifier: Operating System :: OS Independent
Requires-Python: >=3.6
